oon/__init__.py
oon/oon.py
oon-0.0.5.dist-info/LICENSE
oon-0.0.5.dist-info/METADATA
oon-0.0.5.dist-info/WHEEL
oon-0.0.5.dist-info/top_level.txt
oon-0.0.5.dist-info/RECORD
