Metadata-Version: 2.1
Name: oon
Version: 0.0.5
Summary: Package for simplify classes and objects transfer over network
Author: Ivashka (Ivan Rakov)
Author-email: <ivashka.2.r@gmail.com>
Keywords: python,network,sockets,objects,classes,oon
Platform: any
License-File: LICENSE
